fastloom/__init__.py
fastloom/auth/__init__.py
fastloom/auth/depends.py
fastloom/auth/schemas.py
fastloom/cache/__init__.py
fastloom/cache/base.py
fastloom/cache/gate.py
fastloom/cache/healthcheck.py
fastloom/cache/lifehooks.py
fastloom/cache/settings.py
fastloom/crypto.py
fastloom/date.py
fastloom/db/__init__.py
fastloom/db/healthcheck.py
fastloom/db/lifehooks.py
fastloom/db/schemas.py
fastloom/db/settings.py
fastloom/db/signals.py
fastloom/db/transactions.py
fastloom/file/__init__.py
fastloom/file/models.py
fastloom/file/schema.py
fastloom/file/signals.py
fastloom/file/utils.py
fastloom/healthcheck/__init__.py
fastloom/healthcheck/handler.py
fastloom/i18n/__init__.py
fastloom/i18n/base.py
fastloom/i18n/handler.py
fastloom/i18n/settings.py
fastloom/i18n/types.py
fastloom/launcher/__init__.py
fastloom/launcher/main.py
fastloom/launcher/schemas.py
fastloom/launcher/settings.py
fastloom/launcher/utils.py
fastloom/meta.py
fastloom/monitoring.py
fastloom/observability/__init__.py
fastloom/observability/settings.py
fastloom/py.typed
fastloom/settings/__init__.py
fastloom/settings/base.py
fastloom/settings/utils.py
fastloom/signals/__init__.py
fastloom/signals/depends.py
fastloom/signals/healthcheck.py
fastloom/signals/lifehooks.py
fastloom/signals/middlewares.py
fastloom/signals/settings.py
fastloom/tenant/__init__.py
fastloom/tenant/depends.py
fastloom/tenant/handler.py
fastloom/tenant/protocols.py
fastloom/tenant/schemas.py
fastloom/tenant/settings.py
fastloom/tenant/utils.py
fastloom/tests.py
fastloom/types.py
fastloom/utils.py
fastloom-0.4.14.dist-info/METADATA
fastloom-0.4.14.dist-info/WHEEL
fastloom-0.4.14.dist-info/entry_points.txt
fastloom-0.4.14.dist-info/RECORD
